<?xml version="1.0" encoding="utf-8"?>
<SynthSet xmlns:xsd="http://www.w3.org/2001/XMLSchema" xmlns:xsi="http://www.w3.org/2001/XMLSchema-instance">
  <Instruments>
    <Instruments xsi:type="vcaData">
      <ID>-97048</ID>
      <deviceType>VCA</deviceType>
      <position>
        <x>0.367082864</x>
        <y>1.79258943</y>
        <z>0.563266456</z>
      </position>
      <scale>
        <x>0.821903646</x>
        <y>0.821899951</y>
        <z>0.8219035</z>
      </scale>
      <rotation>
        <x>0.0152313123</x>
        <y>0.9311857</y>
        <z>0.148242965</z>
        <w>-0.3326939</w>
      </rotation>
      <dialState>0.194530055</dialState>
      <jackOutID>-97150</jackOutID>
      <jackInID>-97122</jackInID>
      <jackControlID>-97178</jackControlID>
    </Instruments>
    <Instruments xsi:type="ScopeData">
      <ID>-96696</ID>
      <deviceType>Scope</deviceType>
      <position>
        <x>0.129213572</x>
        <y>1.86916018</y>
        <z>0.645336568</z>
      </position>
      <scale>
        <x>0.861800969</x>
        <y>0.8618018</y>
        <z>0.861801744</z>
      </scale>
      <rotation>
        <x>-0.0756473</x>
        <y>-0.0644653</y>
        <z>-0.0115801934</z>
        <w>-0.9949812</w>
      </rotation>
      <jackOutID>-96754</jackOutID>
      <jackInID>-96726</jackInID>
      <periodState>1</periodState>
      <modeState>false</modeState>
      <triggerState>true</triggerState>
      <muteState>false</muteState>
    </Instruments>
    <Instruments xsi:type="vcaData">
      <ID>-96466</ID>
      <deviceType>VCA</deviceType>
      <position>
        <x>-0.319166929</x>
        <y>2.031956</y>
        <z>0.534290552</z>
      </position>
      <scale>
        <x>0.719701469</x>
        <y>0.7196975</y>
        <z>0.719702363</z>
      </scale>
      <rotation>
        <x>0.0229922552</x>
        <y>-0.976849258</y>
        <z>0.00519592175</z>
        <w>-0.212626427</w>
      </rotation>
      <dialState>0.771461666</dialState>
      <jackOutID>-96568</jackOutID>
      <jackInID>-96540</jackInID>
      <jackControlID>-96596</jackControlID>
    </Instruments>
    <Instruments xsi:type="OscillatorData">
      <ID>-95954</ID>
      <deviceType>Oscillator</deviceType>
      <position>
        <x>-0.137226954</x>
        <y>1.8002156</y>
        <z>0.6386604</z>
      </position>
      <scale>
        <x>0.863644063</x>
        <y>0.863636434</y>
        <z>0.8636421</z>
      </scale>
      <rotation>
        <x>0.0223022662</x>
        <y>-0.991172135</y>
        <z>-0.100361563</z>
        <w>-0.08371418</w>
      </rotation>
      <amp>0.8796987</amp>
      <freq>0.5</freq>
      <lfo>false</lfo>
      <wave>0</wave>
      <jackOutID>-96076</jackOutID>
      <jackInAmpID>-96152</jackInAmpID>
      <jackInFreqExpID>-96096</jackInFreqExpID>
      <jackInFreqLinID>-96124</jackInFreqLinID>
      <jackInSyncID>-96406</jackInSyncID>
      <jackInPwmID>-96378</jackInPwmID>
    </Instruments>
    <Instruments xsi:type="NoiseData">
      <ID>-95824</ID>
      <deviceType>Noise</deviceType>
      <position>
        <x>-0.3927824</x>
        <y>2.01168036</y>
        <z>0.429397285</z>
      </position>
      <scale>
        <x>0.532113731</x>
        <y>0.532112956</y>
        <z>0.5321143</z>
      </scale>
      <rotation>
        <x>0.0202872027</x>
        <y>-0.7872597</y>
        <z>0.0176173709</z>
        <w>-0.616036</w>
      </rotation>
      <dialState>0.5648772</dialState>
      <jackOutID>-95860</jackOutID>
    </Instruments>
    <Instruments xsi:type="OscillatorData">
      <ID>-95312</ID>
      <deviceType>Oscillator</deviceType>
      <position>
        <x>-0.2508363</x>
        <y>1.9402777</y>
        <z>0.6028884</z>
      </position>
      <scale>
        <x>0.863642454</x>
        <y>0.8636374</y>
        <z>0.863642454</z>
      </scale>
      <rotation>
        <x>-0.00624023145</x>
        <y>-0.9819357</y>
        <z>-0.0253394116</z>
        <w>-0.187406689</w>
      </rotation>
      <amp>0.552216</amp>
      <freq>0.354771376</freq>
      <lfo>false</lfo>
      <wave>0</wave>
      <jackOutID>-95434</jackOutID>
      <jackInAmpID>-95510</jackInAmpID>
      <jackInFreqExpID>-95454</jackInFreqExpID>
      <jackInFreqLinID>-95482</jackInFreqLinID>
      <jackInSyncID>-95764</jackInSyncID>
      <jackInPwmID>-95736</jackInPwmID>
    </Instruments>
  </Instruments>
  <Plugs>
    <Plugs>
      <ID>-97566</ID>
      <deviceType>AD</deviceType>
      <position>
        <x>-0.138007581</x>
        <y>1.88551307</y>
        <z>0.631481767</z>
      </position>
      <scale>
        <x>1.3255024</x>
        <y>1.32550478</y>
        <z>1.32551122</z>
      </scale>
      <rotation>
        <x>0.09516255</x>
        <y>0.767169952</y>
        <z>-0.6234436</z>
        <w>0.117100954</w>
      </rotation>
      <outputPlug>true</outputPlug>
      <connected>-96124</connected>
      <otherPlug>-97534</otherPlug>
      <plugPath>
        <Vector3>
          <x>-0.182433456</x>
          <y>1.94116223</y>
          <z>0.603839636</z>
        </Vector3>
        <Vector3>
          <x>-0.175076932</x>
          <y>1.93165445</y>
          <z>0.608465135</z>
        </Vector3>
        <Vector3>
          <x>-0.167723969</x>
          <y>1.92218375</y>
          <z>0.613084555</z>
        </Vector3>
        <Vector3>
          <x>-0.160377011</x>
          <y>1.91277325</y>
          <z>0.617694</z>
        </Vector3>
        <Vector3>
          <x>-0.153036773</x>
          <y>1.9034313</y>
          <z>0.6222923</z>
        </Vector3>
        <Vector3>
          <x>-0.1457021</x>
          <y>1.89414668</y>
          <z>0.6268811</z>
        </Vector3>
        <Vector3>
          <x>-0.138370544</x>
          <y>1.88489366</y>
          <z>0.6314647</z>
        </Vector3>
      </plugPath>
      <cordColor>
        <r>0.78039515</r>
        <g>0.561103642</g>
        <b>0.629303038</b>
        <a>1</a>
      </cordColor>
    </Plugs>
    <Plugs>
      <ID>-97534</ID>
      <deviceType>AD</deviceType>
      <position>
        <x>-0.1824334</x>
        <y>1.94116211</y>
        <z>0.6038396</z>
      </position>
      <scale>
        <x>1.02063859</x>
        <y>1.02064312</y>
        <z>1.0206387</z>
      </scale>
      <rotation>
        <x>-0.00613374449</x>
        <y>-0.8269224</y>
        <z>-0.009021746</z>
        <w>0.5622103</w>
      </rotation>
      <outputPlug>false</outputPlug>
      <connected>-95434</connected>
      <otherPlug>-97566</otherPlug>
      <plugPath />
      <cordColor>
        <r>0.129321471</r>
        <g>0.4395395</g>
        <b>0.966532</b>
        <a>1</a>
      </cordColor>
    </Plugs>
    <Plugs>
      <ID>-97502</ID>
      <deviceType>AD</deviceType>
      <position>
        <x>-0.356764019</x>
        <y>2.03000045</y>
        <z>0.517110348</z>
      </position>
      <scale>
        <x>1.2247659</x>
        <y>1.2247721</y>
        <z>1.22476625</z>
      </scale>
      <rotation>
        <x>-0.01995321</x>
        <y>0.54040277</y>
        <z>0.0128202112</z>
        <w>0.841072261</w>
      </rotation>
      <outputPlug>true</outputPlug>
      <connected>-96540</connected>
      <otherPlug>-97470</otherPlug>
      <plugPath>
        <Vector3>
          <x>-0.382914573</x>
          <y>2.01582527</y>
          <z>0.469192028</z>
        </Vector3>
        <Vector3>
          <x>-0.3699627</x>
          <y>2.02227044</y>
          <z>0.492982268</z>
        </Vector3>
        <Vector3>
          <x>-0.357011</x>
          <y>2.02871656</y>
          <z>0.516772449</z>
        </Vector3>
      </plugPath>
      <cordColor>
        <r>0.682955563</r>
        <g>0.959576845</g>
        <b>0.931604</b>
        <a>1</a>
      </cordColor>
    </Plugs>
    <Plugs>
      <ID>-97470</ID>
      <deviceType>AD</deviceType>
      <position>
        <x>-0.382914543</x>
        <y>2.01582527</y>
        <z>0.469192058</z>
      </position>
      <scale>
        <x>1.10435593</x>
        <y>1.10435784</y>
        <z>1.1043576</z>
      </scale>
      <rotation>
        <x>-0.00323899183</x>
        <y>0.99227494</y>
        <z>-0.0265294388</z>
        <w>-0.121146262</w>
      </rotation>
      <outputPlug>false</outputPlug>
      <connected>-95860</connected>
      <otherPlug>-97502</otherPlug>
      <plugPath />
      <cordColor>
        <r>0.919129848</r>
        <g>0.0755024</g>
        <b>0.472805679</b>
        <a>1</a>
      </cordColor>
    </Plugs>
    <Plugs>
      <ID>-97438</ID>
      <deviceType>AD</deviceType>
      <position>
        <x>-0.266946077</x>
        <y>2.024036</y>
        <z>0.574822843</z>
      </position>
      <scale>
        <x>1.32550478</x>
        <y>1.32550478</y>
        <z>1.32551086</z>
      </scale>
      <rotation>
        <x>-0.0181153342</x>
        <y>0.725053966</y>
        <z>-0.6881892</z>
        <w>-0.0190857351</w>
      </rotation>
      <outputPlug>true</outputPlug>
      <connected>-95454</connected>
      <otherPlug>-97406</otherPlug>
      <plugPath>
        <Vector3>
          <x>-0.2817011</x>
          <y>2.033897</y>
          <z>0.5514103</z>
        </Vector3>
        <Vector3>
          <x>-0.274323583</x>
          <y>2.028966</y>
          <z>0.56311667</z>
        </Vector3>
        <Vector3>
          <x>-0.266946137</x>
          <y>2.024036</y>
          <z>0.574822843</z>
        </Vector3>
      </plugPath>
      <cordColor>
        <r>0.536516368</r>
        <g>0.4561097</g>
        <b>0.408064783</b>
        <a>1</a>
      </cordColor>
    </Plugs>
    <Plugs>
      <ID>-97406</ID>
      <deviceType>AD</deviceType>
      <position>
        <x>-0.281701028</x>
        <y>2.03389668</y>
        <z>0.5514103</z>
      </position>
      <scale>
        <x>1.22476578</x>
        <y>1.22477186</y>
        <z>1.22476614</z>
      </scale>
      <rotation>
        <x>0.0127004236</x>
        <y>-0.841070652</y>
        <z>0.0197662357</z>
        <w>0.5404149</w>
      </rotation>
      <outputPlug>false</outputPlug>
      <connected>-96568</connected>
      <otherPlug>-97438</otherPlug>
      <plugPath />
      <cordColor>
        <r>0.364241034</r>
        <g>0.43389374</g>
        <b>0.771252036</b>
        <a>1</a>
      </cordColor>
    </Plugs>
    <Plugs>
      <ID>-97374</ID>
      <deviceType>AD</deviceType>
      <position>
        <x>-0.07039109</x>
        <y>1.80800045</y>
        <z>0.6262508</z>
      </position>
      <scale>
        <x>1.020639</x>
        <y>1.02064335</y>
        <z>1.02063656</z>
      </scale>
      <rotation>
        <x>0.008785127</x>
        <y>-0.764935434</y>
        <z>0.0104354545</z>
        <w>0.6439625</w>
      </rotation>
      <outputPlug>false</outputPlug>
      <connected>-96076</connected>
      <otherPlug>-97342</otherPlug>
      <plugPath />
      <cordColor>
        <r>0.0903551653</r>
        <g>0.431992</g>
        <b>0.8581829</b>
        <a>1</a>
      </cordColor>
    </Plugs>
    <Plugs>
      <ID>-97342</ID>
      <deviceType>AD</deviceType>
      <position>
        <x>-0.0419009179</x>
        <y>1.79464</y>
        <z>0.6567067</z>
      </position>
      <scale>
        <x>1.2785176</x>
        <y>1.27851856</y>
        <z>1.27851915</z>
      </scale>
      <rotation>
        <x>-0.0110434741</x>
        <y>0.7504196</y>
        <z>0.0125421472</z>
        <w>0.6607505</w>
      </rotation>
      <outputPlug>true</outputPlug>
      <connected>-96726</connected>
      <otherPlug>-97374</otherPlug>
      <plugPath>
        <Vector3>
          <x>-0.07039829</x>
          <y>1.80800056</y>
          <z>0.626250863</z>
        </Vector3>
        <Vector3>
          <x>-0.0610472672</x>
          <y>1.803136</y>
          <z>0.636387</z>
        </Vector3>
        <Vector3>
          <x>-0.0516963527</x>
          <y>1.79827225</y>
          <z>0.6465228</z>
        </Vector3>
        <Vector3>
          <x>-0.04234554</x>
          <y>1.79340911</y>
          <z>0.6566582</z>
        </Vector3>
      </plugPath>
      <cordColor>
        <r>0.778395057</r>
        <g>0.0510031059</g>
        <b>0.6686216</b>
        <a>1</a>
      </cordColor>
    </Plugs>
    <Plugs>
      <ID>-97310</ID>
      <deviceType>AD</deviceType>
      <position>
        <x>0.3044352</x>
        <y>1.80355036</y>
        <z>0.6121161</z>
      </position>
      <scale>
        <x>1.27851737</x>
        <y>1.27851856</y>
        <z>1.278519</z>
      </scale>
      <rotation>
        <x>0.0122784153</x>
        <y>-0.6607312</y>
        <z>0.0108106881</z>
        <w>0.7504444</w>
      </rotation>
      <outputPlug>false</outputPlug>
      <connected>-96754</connected>
      <otherPlug>-97278</otherPlug>
      <plugPath />
      <cordColor>
        <r>0.349893838</r>
        <g>0.150403157</g>
        <b>0.0615248755</b>
        <a>1</a>
      </cordColor>
    </Plugs>
    <Plugs>
      <ID>-97278</ID>
      <deviceType>AD</deviceType>
      <position>
        <x>0.332257926</x>
        <y>1.7894417</y>
        <z>0.5911969</z>
      </position>
      <scale>
        <x>1.07247019</x>
        <y>1.07247221</y>
        <z>1.07247043</z>
      </scale>
      <rotation>
        <x>-0.0152435936</x>
        <y>0.901008368</y>
        <z>0.0317659751</z>
        <w>0.4323686</w>
      </rotation>
      <outputPlug>true</outputPlug>
      <connected>-97122</connected>
      <otherPlug>-97310</otherPlug>
      <plugPath>
        <Vector3>
          <x>0.3044352</x>
          <y>1.80355048</y>
          <z>0.612116158</z>
        </Vector3>
        <Vector3>
          <x>0.3135606</x>
          <y>1.79843354</y>
          <z>0.6052552</z>
        </Vector3>
        <Vector3>
          <x>0.322685778</x>
          <y>1.7933172</y>
          <z>0.598394632</z>
        </Vector3>
        <Vector3>
          <x>0.331810743</x>
          <y>1.78820193</y>
          <z>0.5915345</z>
        </Vector3>
      </plugPath>
      <cordColor>
        <r>0.404969275</r>
        <g>0.825449944</g>
        <b>0.9850354</b>
        <a>1</a>
      </cordColor>
    </Plugs>
  </Plugs>
  <Systems>
    <Systems>
      <BPM>120</BPM>
      <binauralMode>0</binauralMode>
      <version>0.45</version>
    </Systems>
  </Systems>
</SynthSet>